{
    "version": "0.4",
    "title": "FAQs",
    "type": "page",
    "metadata": {
        "template_type": "single-page",
        "include_in_zip": "1",
        "elementor_pro_required": null,
        "wp_page_template": "elementor_header_footer"
    },
    "content": [
        {
            "id": "ffc58e4",
            "settings": {
                "content_width": {
                    "unit": "px",
                    "size": 1200,
                    "sizes": []
                },
                "height": "min-height",
                "custom_height": {
                    "unit": "vh",
                    "size": 30,
                    "sizes": []
                },
                "custom_height_tablet": {
                    "unit": "vh",
                    "size": 28,
                    "sizes": []
                },
                "custom_height_mobile": {
                    "unit": "vh",
                    "size": 25,
                    "sizes": []
                },
                "background_background": "classic",
                "background_image": {
                    "url": "http:\/\/askproject.net\/aquwash\/wp-content\/uploads\/sites\/124\/2022\/12\/manual-car-wash-with-pressurized-water-in-car-wash-ANEKKH2.jpg",
                    "id": 338,
                    "alt": "",
                    "source": "library"
                },
                "background_position": "center center",
                "background_size": "cover",
                "background_overlay_background": "classic",
                "background_overlay_color": "#CCB6EB",
                "background_overlay_opacity": {
                    "unit": "px",
                    "size": 0.8,
                    "sizes": []
                },
                "padding": {
                    "unit": "px",
                    "top": "70",
                    "right": "0",
                    "bottom": "70",
                    "left": "0",
                    "isLinked": false
                },
                "padding_tablet": {
                    "unit": "px",
                    "top": "50",
                    "right": "30",
                    "bottom": "50",
                    "left": "30",
                    "isLinked": false
                },
                "padding_mobile": {
                    "unit": "px",
                    "top": "50",
                    "right": "20",
                    "bottom": "50",
                    "left": "20",
                    "isLinked": false
                },
                "transparent": "",
                "transparent_on": [
                    "desktop",
                    "tablet",
                    "mobile"
                ],
                "scroll_distance": {
                    "unit": "px",
                    "size": 60,
                    "sizes": []
                },
                "scroll_distance_tablet": {
                    "unit": "px",
                    "size": "",
                    "sizes": []
                },
                "scroll_distance_mobile": {
                    "unit": "px",
                    "size": "",
                    "sizes": []
                },
                "transparent_header_show": "",
                "background_show": "",
                "background": "",
                "bottom_border": "",
                "custom_bottom_border_color": "",
                "custom_bottom_border_width": {
                    "unit": "px",
                    "size": 0,
                    "sizes": []
                },
                "custom_bottom_border_width_tablet": {
                    "unit": "px",
                    "size": "",
                    "sizes": []
                },
                "custom_bottom_border_width_mobile": {
                    "unit": "px",
                    "size": "",
                    "sizes": []
                },
                "shrink_header": "",
                "custom_height_header": {
                    "unit": "px",
                    "size": 70,
                    "sizes": []
                },
                "custom_height_header_tablet": {
                    "unit": "px",
                    "size": "",
                    "sizes": []
                },
                "custom_height_header_mobile": {
                    "unit": "px",
                    "size": "",
                    "sizes": []
                },
                "shrink_header_logo": "",
                "custom_height_header_logo": {
                    "unit": "px",
                    "size": 70,
                    "sizes": []
                },
                "custom_height_header_logo_tablet": {
                    "unit": "px",
                    "size": "",
                    "sizes": []
                },
                "custom_height_header_logo_mobile": {
                    "unit": "px",
                    "size": "",
                    "sizes": []
                },
                "change_logo_color": "",
                "logo_color_white_before": "",
                "logo_color_black_before": "",
                "logo_color_white_after": "",
                "logo_color_black_after": "",
                "logo_color_full_after": "",
                "blur_bg": "",
                "hide_header": "",
                "scroll_distance_hide_header": {
                    "unit": "px",
                    "size": 500,
                    "sizes": []
                },
                "scroll_distance_hide_header_tablet": {
                    "unit": "px",
                    "size": "",
                    "sizes": []
                },
                "scroll_distance_hide_header_mobile": {
                    "unit": "px",
                    "size": "",
                    "sizes": []
                },
                "background_overlay_color_b": "#B78CF4",
                "background_overlay_gradient_angle": {
                    "unit": "deg",
                    "size": 160,
                    "sizes": []
                },
                "__globals__": {
                    "background_overlay_color": "globals\/colors?id=primary",
                    "background_overlay_color_b": ""
                }
            },
            "elements": [
                {
                    "id": "a32edca",
                    "settings": {
                        "_column_size": 100,
                        "_inline_size": null,
                        "padding": {
                            "unit": "px",
                            "top": "0",
                            "right": "0",
                            "bottom": "0",
                            "left": "0",
                            "isLinked": false
                        }
                    },
                    "elements": [
                        {
                            "id": "bf43de4",
                            "settings": {
                                "title": "FAQs Page",
                                "align": "center",
                                "_margin": {
                                    "unit": "px",
                                    "top": "-15",
                                    "right": "0",
                                    "bottom": "-15",
                                    "left": "0",
                                    "isLinked": false
                                },
                                "_animation": "fadeIn",
                                "__globals__": {
                                    "typography_typography": "globals\/typography?id=primary"
                                },
                                "title_color": "#FFFFFF"
                            },
                            "elements": [],
                            "isInner": false,
                            "widgetType": "heading",
                            "elType": "widget"
                        },
                        {
                            "id": "509f6887",
                            "settings": {
                                "view": "inline",
                                "icon_list": [
                                    {
                                        "text": "Home",
                                        "selected_icon": {
                                            "value": "",
                                            "library": ""
                                        },
                                        "_id": "27597e4",
                                        "link": {
                                            "url": "#",
                                            "is_external": "",
                                            "nofollow": "",
                                            "custom_attributes": ""
                                        }
                                    },
                                    {
                                        "text": "FAQs",
                                        "selected_icon": {
                                            "value": "fas fa-long-arrow-alt-right",
                                            "library": "fa-solid"
                                        },
                                        "_id": "07e293f",
                                        "link": {
                                            "url": "#",
                                            "is_external": "",
                                            "nofollow": "",
                                            "custom_attributes": ""
                                        }
                                    }
                                ],
                                "space_between": {
                                    "unit": "px",
                                    "size": 15,
                                    "sizes": []
                                },
                                "icon_align": "center",
                                "icon_size": {
                                    "unit": "px",
                                    "size": 15,
                                    "sizes": []
                                },
                                "text_indent": {
                                    "unit": "px",
                                    "size": 15,
                                    "sizes": []
                                },
                                "_margin": {
                                    "unit": "px",
                                    "top": "0",
                                    "right": "0",
                                    "bottom": "0",
                                    "left": "-15",
                                    "isLinked": false
                                },
                                "_animation": "fadeIn",
                                "_animation_delay": 200,
                                "__globals__": {
                                    "icon_color": "globals\/colors?id=f204b74",
                                    "text_color": "",
                                    "icon_typography_typography": "globals\/typography?id=accent",
                                    "text_color_hover": "globals\/colors?id=accent"
                                },
                                "icon_color": "#E8FC56",
                                "text_color": "#FFFFFF99",
                                "text_color_hover": "#E8FC56"
                            },
                            "elements": [],
                            "isInner": false,
                            "widgetType": "icon-list",
                            "elType": "widget"
                        }
                    ],
                    "isInner": false,
                    "elType": "column"
                }
            ],
            "isInner": false,
            "elType": "section"
        },
        {
            "id": "62a3a1c1",
            "settings": {
                "content_width": {
                    "unit": "px",
                    "size": 1200,
                    "sizes": []
                },
                "structure": "20",
                "padding": {
                    "unit": "px",
                    "top": "100",
                    "right": "0",
                    "bottom": "100",
                    "left": "0",
                    "isLinked": false
                },
                "padding_tablet": {
                    "unit": "px",
                    "top": "70",
                    "right": "30",
                    "bottom": "70",
                    "left": "30",
                    "isLinked": false
                },
                "padding_mobile": {
                    "unit": "px",
                    "top": "70",
                    "right": "20",
                    "bottom": "70",
                    "left": "20",
                    "isLinked": false
                },
                "__globals__": {
                    "background_color": "globals\/colors?id=6b62ecd"
                }
            },
            "elements": [
                {
                    "id": "823a668",
                    "settings": {
                        "_column_size": 50,
                        "_inline_size": 70,
                        "_inline_size_tablet": 100,
                        "margin": {
                            "unit": "px",
                            "top": "0",
                            "right": "70",
                            "bottom": "0",
                            "left": "0",
                            "isLinked": false
                        },
                        "margin_tablet": {
                            "unit": "px",
                            "top": "0",
                            "right": "0",
                            "bottom": "50",
                            "left": "0",
                            "isLinked": false
                        },
                        "margin_mobile": {
                            "unit": "px",
                            "top": "0",
                            "right": "0",
                            "bottom": "20",
                            "left": "0",
                            "isLinked": false
                        },
                        "padding": {
                            "unit": "px",
                            "top": "0",
                            "right": "0",
                            "bottom": "0",
                            "left": "0",
                            "isLinked": false
                        }
                    },
                    "elements": [
                        {
                            "id": "1451c81a",
                            "settings": {
                                "editor": "<p>FAQs<\/p>",
                                "align": "left",
                                "_margin": {
                                    "unit": "px",
                                    "top": "0",
                                    "right": "0",
                                    "bottom": "-15",
                                    "left": "0",
                                    "isLinked": false
                                },
                                "__globals__": {
                                    "text_color": "globals\/colors?id=accent",
                                    "typography_typography": "globals\/typography?id=ac3559b"
                                },
                                "_animation": "fadeInUp"
                            },
                            "elements": [],
                            "isInner": false,
                            "widgetType": "text-editor",
                            "elType": "widget"
                        },
                        {
                            "id": "44f709be",
                            "settings": {
                                "title": "Frequently Asked Questions",
                                "align": "left",
                                "_margin": {
                                    "unit": "px",
                                    "top": "0",
                                    "right": "0",
                                    "bottom": "0",
                                    "left": "0",
                                    "isLinked": false
                                },
                                "_animation": "fadeInUp",
                                "_animation_delay": 200,
                                "__globals__": {
                                    "typography_typography": "globals\/typography?id=secondary"
                                }
                            },
                            "elements": [],
                            "isInner": false,
                            "widgetType": "heading",
                            "elType": "widget"
                        },
                        {
                            "id": "5e48e3cb",
                            "settings": {
                                "_margin": {
                                    "unit": "px",
                                    "top": "0",
                                    "right": "0",
                                    "bottom": "0",
                                    "left": "0",
                                    "isLinked": false
                                },
                                "_animation": "fadeInUp",
                                "_animation_delay": 400,
                                "__globals__": {
                                    "typography_typography": "globals\/typography?id=text"
                                }
                            },
                            "elements": [],
                            "isInner": false,
                            "widgetType": "text-editor",
                            "elType": "widget"
                        },
                        {
                            "id": "166fd99f",
                            "settings": {
                                "ekit_accordion_items": [
                                    {
                                        "acc_title": "How many fruit flavors do you have?",
                                        "acc_content": "<p>Etiam suscipit, odio nec sagittis imperdiet, quam ante ullamcorper nisl, sed tincidunt ligula nibh ac libero. Praesent et tempor tortor, non aliquet leo.<\/p>",
                                        "ekit_acc_is_active": "yes",
                                        "_id": "7f2bc98"
                                    },
                                    {
                                        "acc_title": "Can I buy you product  in large quantities?",
                                        "acc_content": "<p>Etiam suscipit, odio nec sagittis imperdiet, quam ante ullamcorper nisl, sed tincidunt ligula nibh ac libero. Praesent et tempor tortor, non aliquet leo.<\/p>",
                                        "_id": "e58c15a"
                                    },
                                    {
                                        "acc_title": "How many branches do you have now?",
                                        "acc_content": "<p>Etiam suscipit, odio nec sagittis imperdiet, quam ante ullamcorper nisl, sed tincidunt ligula nibh ac libero. Praesent et tempor tortor, non aliquet leo.<\/p>",
                                        "_id": "a384a67"
                                    },
                                    {
                                        "acc_title": "How do I open a franchise for Connie?",
                                        "acc_content": "<p>Etiam suscipit, odio nec sagittis imperdiet, quam ante ullamcorper nisl, sed tincidunt ligula nibh ac libero. Praesent et tempor tortor, non aliquet leo.<\/p>",
                                        "_id": "3f11b2f"
                                    },
                                    {
                                        "acc_title": "Can I buy you product  in large quantities?",
                                        "acc_content": "<p>Etiam suscipit, odio nec sagittis imperdiet, quam ante ullamcorper nisl, sed tincidunt ligula nibh ac libero. Praesent et tempor tortor, non aliquet leo.<\/p>",
                                        "_id": "c4c9515"
                                    },
                                    {
                                        "acc_title": "How many branches do you have now?",
                                        "acc_content": "<p>Etiam suscipit, odio nec sagittis imperdiet, quam ante ullamcorper nisl, sed tincidunt ligula nibh ac libero. Praesent et tempor tortor, non aliquet leo.<\/p>",
                                        "_id": "84d58d0"
                                    },
                                    {
                                        "acc_title": "How many fruit flavors do you have?",
                                        "acc_content": "<p>Etiam suscipit, odio nec sagittis imperdiet, quam ante ullamcorper nisl, sed tincidunt ligula nibh ac libero. Praesent et tempor tortor, non aliquet leo.<\/p>",
                                        "ekit_acc_is_active": "",
                                        "_id": "6852065"
                                    }
                                ],
                                "ekit_accordion_right_icons": {
                                    "value": "fas fa-chevron-down",
                                    "library": "fa-solid"
                                },
                                "ekit_accordion_right_icon_actives": {
                                    "value": "fas fa-chevron-left",
                                    "library": "fa-solid"
                                },
                                "ekit_accordion_background_background": "classic",
                                "ekit_accordion_title_border_open_border": "solid",
                                "ekit_accordion_title_border_open_width": {
                                    "unit": "px",
                                    "top": "0",
                                    "right": "0",
                                    "bottom": "0",
                                    "left": "0",
                                    "isLinked": true
                                },
                                "ekit_accordion_border_radious_curve_shape_open": {
                                    "unit": "px",
                                    "top": "30",
                                    "right": "30",
                                    "bottom": "30",
                                    "left": "30",
                                    "isLinked": true
                                },
                                "ekit_accordion_background_close_background": "classic",
                                "ekit_accordion_background_close_color": "#F6F6F6",
                                "ekit_accordion_title_border_close_border": "solid",
                                "ekit_accordion_title_border_close_width": {
                                    "unit": "px",
                                    "top": "0",
                                    "right": "0",
                                    "bottom": "0",
                                    "left": "0",
                                    "isLinked": true
                                },
                                "ekit_accordion_border_radious_close": {
                                    "unit": "px",
                                    "top": "30",
                                    "right": "30",
                                    "bottom": "30",
                                    "left": "30",
                                    "isLinked": true
                                },
                                "ekit_accordion_title_padding": {
                                    "unit": "px",
                                    "top": "15",
                                    "right": "50",
                                    "bottom": "15",
                                    "left": "30",
                                    "isLinked": false
                                },
                                "ekit_accordion_content_border_radious": {
                                    "unit": "px",
                                    "top": "0",
                                    "right": "0",
                                    "bottom": "0",
                                    "left": "0",
                                    "isLinked": false
                                },
                                "ekit_accordion_content_padding": {
                                    "unit": "px",
                                    "top": "25",
                                    "right": "30",
                                    "bottom": "15",
                                    "left": "50",
                                    "isLinked": false
                                },
                                "ekit_accordion_content_padding_mobile": {
                                    "unit": "px",
                                    "top": "12",
                                    "right": "20",
                                    "bottom": "15",
                                    "left": "30",
                                    "isLinked": false
                                },
                                "ekit_accordion_closed_icon_border_border": "solid",
                                "ekit_accordion_closed_icon_border_width": {
                                    "unit": "px",
                                    "top": "0",
                                    "right": "0",
                                    "bottom": "0",
                                    "left": "0",
                                    "isLinked": false
                                },
                                "ekit_accordion_icon_border_radious": {
                                    "unit": "px",
                                    "top": "0",
                                    "right": "0",
                                    "bottom": "0",
                                    "left": "0",
                                    "isLinked": false
                                },
                                "ekit_accordion_icon_padding": {
                                    "unit": "px",
                                    "top": "0",
                                    "right": "0",
                                    "bottom": "0",
                                    "left": "0",
                                    "isLinked": false
                                },
                                "ekit_accordion_section_icon_margin": {
                                    "unit": "px",
                                    "top": "0",
                                    "right": "30",
                                    "bottom": "0",
                                    "left": "0",
                                    "isLinked": false
                                },
                                "_margin": {
                                    "unit": "px",
                                    "top": "0",
                                    "right": "0",
                                    "bottom": "0",
                                    "left": "0",
                                    "isLinked": false
                                },
                                "_margin_mobile": {
                                    "unit": "px",
                                    "top": "0",
                                    "right": "0",
                                    "bottom": "0",
                                    "left": "0",
                                    "isLinked": false
                                },
                                "_animation": "fadeInUp",
                                "_animation_delay": 400,
                                "__globals__": {
                                    "ekit_accordion_title_typography_typography": "globals\/typography?id=39482fe",
                                    "ekit_accordion_content_typography_typography": "globals\/typography?id=text",
                                    "ekit_accordion_background_color": "globals\/colors?id=primary",
                                    "ekit_accordion_title_color": "",
                                    "ekit_accordion_title_border_open_color": "",
                                    "ekit_accordion_title_color_close": "globals\/colors?id=primary",
                                    "ekit_accordion_content_color": "globals\/colors?id=text",
                                    "ekit_accordion_icon_color_close": "globals\/colors?id=accent",
                                    "ekit_accordion_icon_color": "globals\/colors?id=f204b74",
                                    "ekit_accordion_background_close_color": "globals\/colors?id=6b62ecd"
                                },
                                "ekit_accordion_title_color": "#FFFFFF",
                                "ekit_accordion_background_color": "#1C202F",
                                "ekit_accordion_title_color_close": "#1C202F",
                                "ekit_accordion_content_color": "#767986",
                                "ekit_accordion_icon_color_close": "#8067FA",
                                "ekit_accordion_icon_color": "#FFF781"
                            },
                            "elements": [],
                            "isInner": false,
                            "widgetType": "elementskit-accordion",
                            "elType": "widget"
                        }
                    ],
                    "isInner": false,
                    "elType": "column"
                },
                {
                    "id": "59d18931",
                    "settings": {
                        "_column_size": 50,
                        "_inline_size": 30,
                        "_inline_size_tablet": 100,
                        "padding": {
                            "unit": "px",
                            "top": "0",
                            "right": "0",
                            "bottom": "0",
                            "left": "0",
                            "isLinked": false
                        }
                    },
                    "elements": [
                        {
                            "id": "508a2bc7",
                            "settings": {
                                "margin": {
                                    "unit": "px",
                                    "top": "0",
                                    "right": 0,
                                    "bottom": "30",
                                    "left": 0,
                                    "isLinked": false
                                },
                                "animation": "fadeIn",
                                "margin_tablet": {
                                    "unit": "px",
                                    "top": "0",
                                    "right": 0,
                                    "bottom": "30",
                                    "left": 0,
                                    "isLinked": false
                                },
                                "transparent": "",
                                "transparent_on": [
                                    "desktop",
                                    "tablet",
                                    "mobile"
                                ],
                                "scroll_distance": {
                                    "unit": "px",
                                    "size": 60,
                                    "sizes": []
                                },
                                "scroll_distance_tablet": {
                                    "unit": "px",
                                    "size": "",
                                    "sizes": []
                                },
                                "scroll_distance_mobile": {
                                    "unit": "px",
                                    "size": "",
                                    "sizes": []
                                },
                                "transparent_header_show": "",
                                "background_show": "",
                                "background": "",
                                "bottom_border": "",
                                "custom_bottom_border_color": "",
                                "custom_bottom_border_width": {
                                    "unit": "px",
                                    "size": 0,
                                    "sizes": []
                                },
                                "custom_bottom_border_width_tablet": {
                                    "unit": "px",
                                    "size": "",
                                    "sizes": []
                                },
                                "custom_bottom_border_width_mobile": {
                                    "unit": "px",
                                    "size": "",
                                    "sizes": []
                                },
                                "shrink_header": "",
                                "custom_height_header": {
                                    "unit": "px",
                                    "size": 70,
                                    "sizes": []
                                },
                                "custom_height_header_tablet": {
                                    "unit": "px",
                                    "size": "",
                                    "sizes": []
                                },
                                "custom_height_header_mobile": {
                                    "unit": "px",
                                    "size": "",
                                    "sizes": []
                                },
                                "shrink_header_logo": "",
                                "custom_height_header_logo": {
                                    "unit": "px",
                                    "size": 70,
                                    "sizes": []
                                },
                                "custom_height_header_logo_tablet": {
                                    "unit": "px",
                                    "size": "",
                                    "sizes": []
                                },
                                "custom_height_header_logo_mobile": {
                                    "unit": "px",
                                    "size": "",
                                    "sizes": []
                                },
                                "change_logo_color": "",
                                "logo_color_white_before": "",
                                "logo_color_black_before": "",
                                "logo_color_white_after": "",
                                "logo_color_black_after": "",
                                "logo_color_full_after": "",
                                "blur_bg": "",
                                "hide_header": "",
                                "scroll_distance_hide_header": {
                                    "unit": "px",
                                    "size": 500,
                                    "sizes": []
                                },
                                "scroll_distance_hide_header_tablet": {
                                    "unit": "px",
                                    "size": "",
                                    "sizes": []
                                },
                                "scroll_distance_hide_header_mobile": {
                                    "unit": "px",
                                    "size": "",
                                    "sizes": []
                                },
                                "padding": {
                                    "unit": "%",
                                    "top": "0",
                                    "right": "0",
                                    "bottom": "0",
                                    "left": "0",
                                    "isLinked": false
                                },
                                "padding_tablet": {
                                    "unit": "%",
                                    "top": "0",
                                    "right": "0",
                                    "bottom": "0",
                                    "left": "0",
                                    "isLinked": false
                                },
                                "padding_mobile": {
                                    "unit": "%",
                                    "top": "",
                                    "right": "",
                                    "bottom": "",
                                    "left": "",
                                    "isLinked": true
                                },
                                "background_image": {
                                    "url": "",
                                    "id": "",
                                    "alt": "",
                                    "source": "library"
                                },
                                "margin_mobile": {
                                    "unit": "px",
                                    "top": "0",
                                    "right": 0,
                                    "bottom": "20",
                                    "left": 0,
                                    "isLinked": false
                                },
                                "__globals__": {
                                    "background_color": "globals\/colors?id=secondary"
                                }
                            },
                            "elements": [
                                {
                                    "id": "36200f33",
                                    "settings": {
                                        "_column_size": 100,
                                        "_inline_size": null,
                                        "background_background": "classic",
                                        "padding": {
                                            "unit": "px",
                                            "top": "40",
                                            "right": "40",
                                            "bottom": "40",
                                            "left": "40",
                                            "isLinked": true
                                        },
                                        "border_radius": {
                                            "unit": "px",
                                            "top": "20",
                                            "right": "20",
                                            "bottom": "20",
                                            "left": "20",
                                            "isLinked": true
                                        },
                                        "__globals__": {
                                            "background_color": "globals\/colors?id=secondary",
                                            "background_overlay_color": "globals\/colors?id=secondary"
                                        },
                                        "padding_mobile": {
                                            "unit": "px",
                                            "top": "30",
                                            "right": "30",
                                            "bottom": "30",
                                            "left": "30",
                                            "isLinked": true
                                        },
                                        "background_image": {
                                            "url": "http:\/\/askproject.net\/aquwash\/wp-content\/uploads\/sites\/124\/2022\/12\/woman-working-at-customer-service-compan-FFUJGSN.jpg",
                                            "id": 283,
                                            "alt": "",
                                            "source": "library"
                                        },
                                        "background_position": "center center",
                                        "background_size": "cover",
                                        "background_overlay_background": "classic",
                                        "background_overlay_opacity": {
                                            "unit": "px",
                                            "size": 0.9,
                                            "sizes": []
                                        }
                                    },
                                    "elements": [
                                        {
                                            "id": "daa8457",
                                            "settings": {
                                                "title": "Our Office",
                                                "header_size": "h5",
                                                "__globals__": {
                                                    "typography_typography": "globals\/typography?id=989e21d",
                                                    "title_color": "globals\/colors?id=primary"
                                                },
                                                "_margin": {
                                                    "unit": "px",
                                                    "top": "-4",
                                                    "right": "0",
                                                    "bottom": "0",
                                                    "left": "0",
                                                    "isLinked": false
                                                }
                                            },
                                            "elements": [],
                                            "isInner": false,
                                            "widgetType": "heading",
                                            "elType": "widget"
                                        },
                                        {
                                            "id": "460b9e43",
                                            "settings": {
                                                "icon_list": [
                                                    {
                                                        "text": "457 Morningview Lane NY",
                                                        "selected_icon": {
                                                            "value": "fas fa-map-marker-alt",
                                                            "library": "fa-solid"
                                                        },
                                                        "_id": "6435ead",
                                                        "link": {
                                                            "url": "#",
                                                            "is_external": "",
                                                            "nofollow": "",
                                                            "custom_attributes": ""
                                                        }
                                                    },
                                                    {
                                                        "text": "aquwash@mails.com",
                                                        "selected_icon": {
                                                            "value": "fas fa-envelope",
                                                            "library": "fa-solid"
                                                        },
                                                        "_id": "ed97136",
                                                        "link": {
                                                            "url": "#",
                                                            "is_external": "",
                                                            "nofollow": "",
                                                            "custom_attributes": ""
                                                        }
                                                    },
                                                    {
                                                        "text": "+1 (234) 567 890",
                                                        "selected_icon": {
                                                            "value": "fas fa-phone-alt",
                                                            "library": "fa-solid"
                                                        },
                                                        "_id": "e0df306",
                                                        "link": {
                                                            "url": "#",
                                                            "is_external": "",
                                                            "nofollow": "",
                                                            "custom_attributes": ""
                                                        }
                                                    }
                                                ],
                                                "space_between": {
                                                    "unit": "px",
                                                    "size": 10,
                                                    "sizes": []
                                                },
                                                "text_indent": {
                                                    "unit": "px",
                                                    "size": 10,
                                                    "sizes": []
                                                },
                                                "_margin": {
                                                    "unit": "px",
                                                    "top": "-5",
                                                    "right": "0",
                                                    "bottom": "0",
                                                    "left": "0",
                                                    "isLinked": false
                                                },
                                                "__globals__": {
                                                    "text_color": "globals\/colors?id=text",
                                                    "text_color_hover": "globals\/colors?id=accent",
                                                    "icon_typography_typography": "",
                                                    "icon_color": "globals\/colors?id=accent"
                                                },
                                                "icon_color": "#D41343",
                                                "text_color_hover": "#D41343"
                                            },
                                            "elements": [],
                                            "isInner": false,
                                            "widgetType": "icon-list",
                                            "elType": "widget"
                                        }
                                    ],
                                    "isInner": true,
                                    "elType": "column"
                                }
                            ],
                            "isInner": true,
                            "elType": "section"
                        },
                        {
                            "id": "4ba4c164",
                            "settings": {
                                "margin": {
                                    "unit": "px",
                                    "top": "0",
                                    "right": 0,
                                    "bottom": "0",
                                    "left": 0,
                                    "isLinked": false
                                },
                                "animation": "fadeIn",
                                "margin_tablet": {
                                    "unit": "px",
                                    "top": "0",
                                    "right": 0,
                                    "bottom": "0",
                                    "left": 0,
                                    "isLinked": false
                                },
                                "transparent": "",
                                "transparent_on": [
                                    "desktop",
                                    "tablet",
                                    "mobile"
                                ],
                                "scroll_distance": {
                                    "unit": "px",
                                    "size": 60,
                                    "sizes": []
                                },
                                "scroll_distance_tablet": {
                                    "unit": "px",
                                    "size": "",
                                    "sizes": []
                                },
                                "scroll_distance_mobile": {
                                    "unit": "px",
                                    "size": "",
                                    "sizes": []
                                },
                                "transparent_header_show": "",
                                "background_show": "",
                                "background": "",
                                "bottom_border": "",
                                "custom_bottom_border_color": "",
                                "custom_bottom_border_width": {
                                    "unit": "px",
                                    "size": 0,
                                    "sizes": []
                                },
                                "custom_bottom_border_width_tablet": {
                                    "unit": "px",
                                    "size": "",
                                    "sizes": []
                                },
                                "custom_bottom_border_width_mobile": {
                                    "unit": "px",
                                    "size": "",
                                    "sizes": []
                                },
                                "shrink_header": "",
                                "custom_height_header": {
                                    "unit": "px",
                                    "size": 70,
                                    "sizes": []
                                },
                                "custom_height_header_tablet": {
                                    "unit": "px",
                                    "size": "",
                                    "sizes": []
                                },
                                "custom_height_header_mobile": {
                                    "unit": "px",
                                    "size": "",
                                    "sizes": []
                                },
                                "shrink_header_logo": "",
                                "custom_height_header_logo": {
                                    "unit": "px",
                                    "size": 70,
                                    "sizes": []
                                },
                                "custom_height_header_logo_tablet": {
                                    "unit": "px",
                                    "size": "",
                                    "sizes": []
                                },
                                "custom_height_header_logo_mobile": {
                                    "unit": "px",
                                    "size": "",
                                    "sizes": []
                                },
                                "change_logo_color": "",
                                "logo_color_white_before": "",
                                "logo_color_black_before": "",
                                "logo_color_white_after": "",
                                "logo_color_black_after": "",
                                "logo_color_full_after": "",
                                "blur_bg": "",
                                "hide_header": "",
                                "scroll_distance_hide_header": {
                                    "unit": "px",
                                    "size": 500,
                                    "sizes": []
                                },
                                "scroll_distance_hide_header_tablet": {
                                    "unit": "px",
                                    "size": "",
                                    "sizes": []
                                },
                                "scroll_distance_hide_header_mobile": {
                                    "unit": "px",
                                    "size": "",
                                    "sizes": []
                                },
                                "padding": {
                                    "unit": "%",
                                    "top": "0",
                                    "right": "0",
                                    "bottom": "0",
                                    "left": "0",
                                    "isLinked": false
                                },
                                "padding_tablet": {
                                    "unit": "%",
                                    "top": "0",
                                    "right": "0",
                                    "bottom": "0",
                                    "left": "0",
                                    "isLinked": false
                                },
                                "padding_mobile": {
                                    "unit": "%",
                                    "top": "",
                                    "right": "",
                                    "bottom": "",
                                    "left": "",
                                    "isLinked": true
                                },
                                "__globals__": {
                                    "background_color": "globals\/colors?id=secondary"
                                }
                            },
                            "elements": [
                                {
                                    "id": "1afba4d9",
                                    "settings": {
                                        "_column_size": 100,
                                        "_inline_size": null,
                                        "background_background": "classic",
                                        "padding": {
                                            "unit": "px",
                                            "top": "40",
                                            "right": "40",
                                            "bottom": "40",
                                            "left": "40",
                                            "isLinked": true
                                        },
                                        "border_radius": {
                                            "unit": "px",
                                            "top": "20",
                                            "right": "20",
                                            "bottom": "20",
                                            "left": "20",
                                            "isLinked": true
                                        },
                                        "__globals__": {
                                            "background_color": "globals\/colors?id=secondary"
                                        },
                                        "padding_mobile": {
                                            "unit": "px",
                                            "top": "30",
                                            "right": "30",
                                            "bottom": "30",
                                            "left": "30",
                                            "isLinked": true
                                        }
                                    },
                                    "elements": [
                                        {
                                            "id": "47897da8",
                                            "settings": {
                                                "title": "Ask us anything",
                                                "header_size": "h5",
                                                "__globals__": {
                                                    "typography_typography": "globals\/typography?id=989e21d",
                                                    "title_color": "globals\/colors?id=primary"
                                                },
                                                "_margin": {
                                                    "unit": "px",
                                                    "top": "-4",
                                                    "right": "0",
                                                    "bottom": "0",
                                                    "left": "0",
                                                    "isLinked": false
                                                }
                                            },
                                            "elements": [],
                                            "isInner": false,
                                            "widgetType": "heading",
                                            "elType": "widget"
                                        },
                                        {
                                            "id": "16f07c0a",
                                            "settings": {
                                                "ekit_wpform_form_id": "302",
                                                "ekit_wpForms_text_color_label": "#FFFFFF",
                                                "ekit_wpForms_field_bg_color": "#FFFFFF",
                                                "ekit_wpForms_field_border_border": "solid",
                                                "ekit_wpForms_field_border_width": {
                                                    "unit": "px",
                                                    "top": "0",
                                                    "right": "0",
                                                    "bottom": "0",
                                                    "left": "0",
                                                    "isLinked": false
                                                },
                                                "ekit_wpForms_field_radius": {
                                                    "unit": "px",
                                                    "top": "30",
                                                    "right": "30",
                                                    "bottom": "30",
                                                    "left": "30",
                                                    "isLinked": true
                                                },
                                                "ekit_wpForms_field_padding": {
                                                    "unit": "px",
                                                    "top": "15",
                                                    "right": "20",
                                                    "bottom": "15",
                                                    "left": "25",
                                                    "isLinked": false
                                                },
                                                "ekit_wpForms_field_description_text_color": "#FFFFFF",
                                                "ekit_wpForms_button_align_mobile": "center",
                                                "ekit_wpForms_button_width_mobile": {
                                                    "unit": "px",
                                                    "size": 160,
                                                    "sizes": []
                                                },
                                                "ekit_wpForms_button_border_normal_border": "solid",
                                                "ekit_wpForms_button_border_normal_width": {
                                                    "unit": "px",
                                                    "top": "0",
                                                    "right": "0",
                                                    "bottom": "0",
                                                    "left": "0",
                                                    "isLinked": false
                                                },
                                                "ekit_wpForms_button_border_radius": {
                                                    "unit": "px",
                                                    "top": "30",
                                                    "right": "30",
                                                    "bottom": "30",
                                                    "left": "30",
                                                    "isLinked": true
                                                },
                                                "ekit_wpForms_button_padding": {
                                                    "unit": "px",
                                                    "top": "15",
                                                    "right": "32",
                                                    "bottom": "15",
                                                    "left": "32",
                                                    "isLinked": false
                                                },
                                                "ekit_wpForms_button_text_color_hover": "#FFFFFF",
                                                "_margin": {
                                                    "unit": "px",
                                                    "top": "-34",
                                                    "right": "0",
                                                    "bottom": "-24",
                                                    "left": "0",
                                                    "isLinked": false
                                                },
                                                "_margin_tablet": {
                                                    "unit": "px",
                                                    "top": "-34",
                                                    "right": "0",
                                                    "bottom": "-24",
                                                    "left": "0",
                                                    "isLinked": false
                                                },
                                                "_margin_mobile": {
                                                    "unit": "px",
                                                    "top": "-34",
                                                    "right": "0",
                                                    "bottom": "-24",
                                                    "left": "0",
                                                    "isLinked": false
                                                },
                                                "__globals__": {
                                                    "ekit_wpForms_field_text_color": "globals\/colors?id=primary",
                                                    "ekit_wpForms_field_typography_typography": "globals\/typography?id=text",
                                                    "ekit_wpForms_text_color_placeholder": "globals\/colors?id=text",
                                                    "ekit_wpForms_button_typography_typography": "globals\/typography?id=accent",
                                                    "ekit_wpForms_button_bg_color_normal": "globals\/colors?id=primary",
                                                    "ekit_wpForms_button_text_color_normal": "globals\/colors?id=6b62ecd",
                                                    "ekit_wpForms_button_bg_color_hover": "globals\/colors?id=accent",
                                                    "ekit_wpForms_typography_label_typography": "globals\/typography?id=accent",
                                                    "ekit_wpForms_field_description_typography_typography": "globals\/typography?id=text"
                                                }
                                            },
                                            "elements": [],
                                            "isInner": false,
                                            "widgetType": "elementskit-wp-forms",
                                            "elType": "widget"
                                        }
                                    ],
                                    "isInner": true,
                                    "elType": "column"
                                }
                            ],
                            "isInner": true,
                            "elType": "section"
                        }
                    ],
                    "isInner": false,
                    "elType": "column"
                }
            ],
            "isInner": false,
            "elType": "section"
        }
    ],
    "page_settings": {
        "hide_title": "yes",
        "template": "elementor_header_footer"
    }
}